bash_wizard/__init__.py
bash_wizard/__main__.py
bash_wizard-0.0.1.dist-info/LICENSE
bash_wizard-0.0.1.dist-info/METADATA
bash_wizard-0.0.1.dist-info/WHEEL
bash_wizard-0.0.1.dist-info/entry_points.txt
bash_wizard-0.0.1.dist-info/top_level.txt
bash_wizard-0.0.1.dist-info/RECORD
