Metadata-Version: 2.1
Name: bash_wizard
Version: 0.0.1
Summary: An AI powered wizard to bash commands
Maintainer-email: Alexandre Prates <ajfprates@gmail.com>
License: MIT License
Project-URL: Source, https://github.com/alexandreprates/bash_wizard
Requires-Python: >=3.10
License-File: LICENSE
Requires-Dist: ollama >=0.3.0
Requires-Dist: requests >=2.32.3
Requires-Dist: bashcolor >=1.1.1
